[{"post_date":"2023-08-16 09:29:02","post_title":"GREECE GOLDEN VISA 2023","post_name":"greece-golden-visa-2023","post_content":"","post_status":"publish","post_excerpt":"","post_password":"Citizenshipinvest2023@programpage","featured_image":false,"metas":{"_wpml_media_featured":"1","_wpml_media_duplicate":"1","_alp_processed":"1694611012","_wpml_word_count":"{\"total\":68,\"to_translate\":{\"ar\":68,\"zh-hant\":68,\"fr\":68,\"ku\":68,\"fa\":68,\"ru\":68,\"es\":68}}","_wp_page_template":"antigua_barbuda_2.php","_pys_head_footer":"a:7:{s:14:\"disable_global\";b:0;s:8:\"head_any\";s:0:\"\";s:12:\"head_desktop\";s:0:\"\";s:11:\"head_mobile\";s:0:\"\";s:10:\"footer_any\";s:0:\"\";s:14:\"footer_desktop\";s:0:\"\";s:13:\"footer_mobile\";s:0:\"\";}","_yoast_wpseo_focuskeywords":"[]","_yoast_wpseo_keywordsynonyms":"[\"Greece Residency by Investment\"]","_yoast_wpseo_estimated-reading-time-minutes":"","program_menu_title":"قائمة البرنامج","_program_menu_title":"field_64d154f84f689","program_menu_overview":"نظرة عامة","_program_menu_overview":"field_64d154f84f6db","program_menu_benifits":"الفوائد","_program_menu_benifits":"field_64d154f84f72b","program_menu_visa":"الدول المعفاة من تأشيرة الدخول","_program_menu_visa":"field_64d154f84f77b","program_menu_costs":"التكاليف","_program_menu_costs":"field_64d154f84f7ca","program_menu_timeline":"الجدول الزمني","_program_menu_timeline":"field_64d154f84f819","program_menu_faqs":"الأسئلة الشائعة","_program_menu_faqs":"field_64d154f84f8a3","program_menu_brochure":"كتيب","_program_menu_brochure":"field_64d154f84f901","program_menu_brochure_file":"","_program_menu_brochure_file":"field_64d154f84f95f","program_menu_title_copy":"قائمة البرنامج","_program_menu_title_copy":"field_64d154f84fa04","program_menu_overview_copy":"نظرة عامة","_program_menu_overview_copy":"field_64d154f84fa55","program_menu_benifits_copy":"فوائد","_program_menu_benifits_copy":"field_64d154f84faa6","program_menu_visa_copy":"الدول الخالية من التأشيرة","_program_menu_visa_copy":"field_64d154f84faf7","program_menu_costs_copy":"التكاليف","_program_menu_costs_copy":"field_64d154f84fb47","program_menu_timeline_copy":"الجدول الزمني","_program_menu_timeline_copy":"field_64d154f84fc12","program_menu_faqs_copy":"الأسئلة المتكررة","_program_menu_faqs_copy":"field_64d154f84fc6e","program_menu_brochure_copy":"كتيب","_program_menu_brochure_copy":"field_64d154f84fcbe","program_menu_brochure_file_copy":"","_program_menu_brochure_file_copy":"field_64d154f84fd0f","section_1_image_hero":{"post_title":"A beautiful photo of Greece Main landmark showing the allure of Greece Golden Visa Header","post_content":"","post_excerpt":"","url":"https:\/\/www.citizenshipinvest.com\/wp-content\/uploads\/2023\/09\/gREECE-Banner-Website-1-1.webp","_wp_attachment_image_alt":"A beautiful photo of Greece Main landmark showing the allure of Greece Golden Visa Header"},"_section_1_image_hero":"field_64d154f84fdb1","section_1_image_logo":{"post_title":"Greece Country Crest in a Silver Circle","post_content":"","post_excerpt":"","url":"https:\/\/www.citizenshipinvest.com\/wp-content\/uploads\/2023\/08\/Greece-1.png","_wp_attachment_image_alt":"Greece Country Crest in a Silver Circle"},"_section_1_image_logo":"field_64d154f84fe02","section_1_title":"Citizenship Invest","_section_1_title":"field_64d154f84fe52","section_1_subtitle":"المستثمرون الأجانب","_section_1_subtitle":"field_64d154f84fea3","section_1_description":"ابحث عن حرية السفر والحياة المستدامة. احصل على الجنسية الثانية عبر الاستثمار.","_section_1_description":"field_64d154f84fef5","section_2_title":"أفضل خدمة","_section_2_title":"field_64d154f84ff96","section_2_description":"نقدم خدمات احترافية وشخصية عالية الجودة لعملائنا.","_section_2_description":"field_64d154f84ffe6","section_2_image":{"post_title":"Greece Country Emblem","post_content":"","post_excerpt":"","url":"https:\/\/www.citizenshipinvest.com\/wp-content\/uploads\/2023\/08\/Greece.webp","_wp_attachment_image_alt":"Greece Country Emblem"},"_section_2_image":"field_64d154f850037","section_3_title":"برامج الجنسية","_section_3_title":"field_64d154f8500de","section_3_list":"5","_section_3_list":"field_64d154f85012e","section_3_bottom_text":"GREECE RESIDENCY BY INVESTMENT LAW","_section_3_bottom_text":"field_64d154f85017d","section_3_collapsed":"On 18’th April 2013, Greece introduced Law 4146\/2013 giving Non-EU citizens and their family members the right to obtain Residency Permits by investing in Real Estate in Greece. The allowance for these types of residency permits has been integrated into the existing Law 3386\/2005 “Entry residence and social integration of third-country nationals in Greece.”\r\n<br><br>\r\nAccording to Article 36A of the Law, a five-year Residency Permit can be granted to Non-EU citizens who own or purchase real estate in Greece, the value of which exceeds 250,000 euro.\r\nIn July 2015, Greece introduced new amendments to Law 4251\/2014 under the Law 4332\/2015, giving Non-EU citizens the right to obtain citizenship if they reside in Greece for 7 consecutive years, providing they stay in Greece for a minimum of 180 days for each year.","_section_3_collapsed":"field_64d154f8501cc","section_4_title":"شهادات عملائنا","_section_4_title":"field_64d154f85026c","section_4_card":"3","_section_4_card":"field_64d154f8502bd","section_5_title":"اتصل بنا","_section_5_title":"field_64d154f85035b","section_5_description":"تواصل معنا اليوم للحصول على استشارة مجانية.","_section_5_description":"field_64d154f8503ac","section_5_bottom_text":"VIEW LIST","_section_5_bottom_text":"field_64d154f8503fb","section_5_countries_number":"27","_section_5_countries_number":"field_64d154f85044a","section_5_all_countries":"1","_section_5_all_countries":"field_64d154f85049a","section_5_countries_note":"*قد يتغير قائمة البلدان حسب سياسة كل حكومة، وكذلك الوصول إلى هذه البلدان.","_section_5_countries_note":"field_64d154f8504e8","section_6_hide":"0","_section_6_hide":"field_64d154f850589","section_6_video_thumbnail":{"post_title":"Layer 1","post_content":"","post_excerpt":"","url":"https:\/\/www.citizenshipinvest.com\/wp-content\/uploads\/2023\/08\/Layer-1.jpg"},"_section_6_video_thumbnail":"field_6494756b21fb0","section_6_video_link":"https:\/\/www.youtube.com\/watch؟v=LsJbJuxGCUw","_section_6_video_link":"field_6494758721fb1","section_6_title":"","_section_6_title":"field_64d154f85067b","section_6_description":"","_section_6_description":"field_64d154f8506cb","section_7_title":"قم بالقراءة أكثر","_section_7_title":"field_64d154f85076b","section_7_description":"ليكون مؤهلاً للحصول على إقامة في اليونان عبر برنامج الإقامة عن طريق الاستثمار، يجب على المتقدمين الاستثمار في العقارات في أي مكان في اليونان للحصول على تأشيرة الذهب.","_section_7_description":"field_64d154f8507c3","section_7_options":"1","_section_7_options":"field_64d154f85fe97","section_7_bottom_title":"تكاليف أخرى","_section_7_bottom_title":"field_64d154f85ff09","section_7_bottom_description":"بالإضافة إلى الاستثمار المطلوب، هناك تكاليف أخرى لبرنامج الإقامة في اليونان عن طريق الاستثمار، وهي رسوم محترفي Citizenship Invest، وتوثيق الوثائق عند الاقتضاء، رسوم البريد والمصاريف الصغيرة الأخرى. الرجاء التواصل معنا إذا كنت ترغب في تلقي اقتباس مفصل يوضح جميع التكاليف.","_section_7_bottom_description":"field_64d154f85ff59","section_8_hide":"1","_section_8_hide":"field_64d154f85ffe6","section_8_title":"الاستعلام <br> وفحوصات الخلفية","_section_8_title":"field_64d154f86002b","section_8_subtitle":"التي تنطبق على جميع خيارات الاستثمار","_section_8_subtitle":"field_64d154f860070","section_8_description":"Citizenship Invest assigns a Document Collection Specialist to each case. By requesting the bare minimum from clients, the firm provides a bespoke service that simplifies the application process. Our job is to make document collection as easy as possible for the client, and when necessary, we obtain documents without their involvement. Please note that the list below is only a starting point. After assessing the specific case, Citizenship Invest creates a personalised checklist.","_section_8_description":"field_64d154f8600d6","section_8_list_title":"DUE DILIGENCE FEES","_section_8_list_title":"field_64d154f860135","section_8_list":"1","_section_8_list":"field_64d154f860187","section_8_image":{"post_title":"appl-4","post_content":"","post_excerpt":"","url":"https:\/\/www.citizenshipinvest.com\/wp-content\/uploads\/2023\/08\/appl-4.jpg"},"_section_8_image":"field_64d154f8601f4","section_8_list_2_title":"DUE DILIGENCE PROCESS","_section_8_list_2_title":"field_64d154f860276","section_8_list_2_bold_title":"Due diligence normally takes four to six weeks to complete and includes the following checks:","_section_8_list_2_bold_title":"field_64d154f8602c5","section_8_list_2":"4","_section_8_list_2":"field_64d154f86030f","section_8_hide_bottom":"1","_section_8_hide_bottom":"field_64d154f86035d","section_8_bottom_title":"INVESTMENT SECURITY","_section_8_bottom_title":"field_64d154f8603c6","section_8_bottom_description":"Investing in the Vanuatu Citizenship Program is a wise decision, as it offers a highly secure avenue for investment. The program has enticed a significant number of affluent investors, and Citizenship Invest boasts an impressive track record of accomplishments.","_section_8_bottom_description":"field_64d154f860434","section_9_title":"APPLICATION PROCESS AND TIMELINE","_section_9_title":"field_64d154f8604d2","section_9_description":"The time frame for obtaining the Greek Golden Visa approval depends on the processing time for due diligence and the individual's case.","_section_9_description":"field_64d154f860538","section_9_list":"4","_section_9_list":"field_64d154f86058e","section_10_hide":"0","_section_10_hide":"field_64d154f86064a","section_10_title":"DOWNLOAD <br> GREEK RESIDENCY<br> BROCHURE","_section_10_title":"field_64d154f860693","section_10_list_title":"CONTENT","_section_10_list_title":"field_64d154f8606d9","section_10_list_1":"<ul>\r\n \t<li>نظرة عامة على البرنامج<\/li>\r\n \t<li>قانون الجنسية<\/li>\r\n \t<li>الفوائد المترتبة على البرنامج<\/li>\r\n \t<li>متطلبات المتقدمين<\/li>\r\n<\/ul>","_section_10_list_1":"field_64d154f86071e","section_10_list_2":"<ul>\r\n \t<li>متطلبات الاستثمار<\/li>\r\n \t<li>رسوم التقديم<\/li>\r\n \t<li>قائمة التوثيقات المطلوبة<\/li>\r\n \t<li>قائمة الدول التي تُمنح تأشيرة دخول أو تأشيرة بدون تأشيرة<\/li>\r\n<\/ul>","_section_10_list_2":"field_64d154f860763","section_10_button":"تنزيل","_section_10_button":"field_64d154f8607b1","section_10_button_link":"","_section_10_button_link":"field_64d154f8607f7","section_10_size":"15 صفحة، 700كب","_section_10_size":"field_64d154f86083a","section_10_image":{"post_title":"Layer 155 copy","post_content":"","post_excerpt":"","url":"https:\/\/www.citizenshipinvest.com\/wp-content\/uploads\/2023\/08\/Layer-155-copy.png"},"_section_10_image":"field_64d154f86087e","section_11_title":"متطلبات الأهلية","_section_11_title":"field_64d154f860929","section_11_cards":"4","_section_11_cards":"field_64d154f86097c","section_11_bottom_title":"الوثائق المطلوبة","_section_11_bottom_title":"field_64d154f8609cb","section_11_bottom_description":"في Citizenship Invest، نُخصص أخصائي جمع الوثائق المكلف لكل حالة، مما يُبسِّط عملية التقديم ويُقلِّل من الأوراق الرسمية. يمكننا أيضًا الحصول على الوثائق اللازمة نيابة عن عملائنا إذا طُلب ذلك. يُرجى ملاحظة أن القائمة التالية هي للإرشاد فقط وليست نصيحة قانونية. بعد تقييم حالتك، نقوم بإنشاء قائمة تحقق مخصصة لتسهيل عملية جمع الوثائق بدون عناء.","_section_11_bottom_description":"field_64d154f860a21","section_11_bottom_text":"عرض جميع الوثائق المطلوبة","_section_11_bottom_text":"field_64d154f860a8b","section_11_bottom_list":"5","_section_11_bottom_list":"field_64d154f860ae4","section_12_title":"الأسئلة المتكررة","_section_12_title":"field_64d154f860ba3","section_12_description":"الأسئلة المتكررة","_section_12_description":"field_64d154f860bff","section_12_image":{"post_title":"Greece Country Emblem","post_content":"","post_excerpt":"","url":"https:\/\/www.citizenshipinvest.com\/wp-content\/uploads\/2023\/08\/Greece.webp","_wp_attachment_image_alt":"Greece Country Emblem"},"_section_12_image":"field_64d154f860c48","section_12_list":"8","_section_12_list":"field_64d154f860c8d","section_13_title":"اتصل بمستشار","_section_13_title":"field_64d154f860d16","section_13_first_name":"الاسم الأول","_section_13_first_name":"field_64d154f860d5a","section_13_last_name":"اسم العائلة","_section_13_last_name":"field_64d154f860da8","section_13_budget":"ميزانية الاستثمار","_section_13_budget":"field_64d154f860df7","section_13_program_of_interest":"البرنامج المهتم به","_section_13_program_of_interest":"field_64d154f860e50","section_13_email":"عنوان البريد الإلكتروني","_section_13_email":"field_64d154f860ea9","section_13_number":"رقم الهاتف","_section_13_number":"field_64d154f860efe","section_13_nationality":"الجنسية","_section_13_nationality":"field_64d154f860f56","section_13_current_country":"بلد الإقامة","_section_13_current_country":"field_64d154f860fad","section_13_question":"استفسارك","_section_13_question":"field_64d154f861001","section_13_button":"إرسال","_section_13_button":"field_64d154f861056","section_14_title":"توصيات","_section_14_title":"field_64d154f8610fe","section_14_list":"4","_section_14_list":"field_64d154f86117e","section_15_title":"اشترك في نشرتنا الإخبارية","_section_15_title":"field_64d154f861230","section_15_input":"أدخل عنوان البريد الإلكتروني","_section_15_input":"field_64d154f861280","section_15_button":"اشتراك","_section_15_button":"field_64d154f8612ce","section_5_countries_text":"البلدان","_section_5_countries_text":"field_6494755021fae","section_3_list_0_Icon":{"post_title":"ovricon-1","post_content":"","post_excerpt":"","url":"https:\/\/www.citizenshipinvest.com\/wp-content\/uploads\/2023\/08\/ovricon-1.jpg"},"_section_3_list_0_Icon":"field_64d154fe2b672","section_3_list_0_Name":"وقت المعالجة","_section_3_list_0_Name":"field_64d154fe2bbaf","section_3_list_0_Description":"الوقت المتوسط لمعالجة طلب الحصول على إقامة في اليونان هو 2-3 أشهر.","_section_3_list_0_Description":"field_64d154fe2bdcb","section_3_list_1_Icon":{"post_title":"ovricon-2","post_content":"","post_excerpt":"","url":"https:\/\/www.citizenshipinvest.com\/wp-content\/uploads\/2023\/08\/ovricon-2.jpg"},"_section_3_list_1_Icon":"field_64d154fe2b672","section_3_list_1_Name":"السفر بدون تأشيرة","_section_3_list_1_Name":"field_64d154fe2bbaf","section_3_list_1_Description":"حاملو إقامة اليونان لديهم حرية الدخول بدون تأشيرة إلى 27 دولة أوروبية في منطقة شنغن","_section_3_list_1_Description":"field_64d154fe2bdcb","section_3_list_2_Icon":{"post_title":"ovricon-3","post_content":"","post_excerpt":"","url":"https:\/\/www.citizenshipinvest.com\/wp-content\/uploads\/2023\/08\/ovricon-3.jpg"},"_section_3_list_2_Icon":"field_64d154fe2b672","section_3_list_2_Name":"نوع الاستثمار","_section_3_list_2_Name":"field_64d154fe2bbaf","section_3_list_2_Description":"الاستثمار في العقارات في اليونان.","_section_3_list_2_Description":"field_64d154fe2bdcb","section_3_list_3_Icon":{"post_title":"ovricon-4","post_content":"","post_excerpt":"","url":"https:\/\/www.citizenshipinvest.com\/wp-content\/uploads\/2023\/08\/ovricon-4.jpg"},"_section_3_list_3_Icon":"field_64d154fe2b672","section_3_list_3_Name":"تكلفة الاستثمار","_section_3_list_3_Name":"field_64d154fe2bbaf","section_3_list_3_Description":"يجب أن يستثمر المتقدم ما لا يقل عن 250،000 يورو في العقارات للحصول على تأشيرة الذهبية اليونانية.","_section_3_list_3_Description":"field_64d154fe2bdcb","section_3_list_4_Icon":{"post_title":"ovricon-5","post_content":"","post_excerpt":"","url":"https:\/\/www.citizenshipinvest.com\/wp-content\/uploads\/2023\/08\/ovricon-5.jpg"},"_section_3_list_4_Icon":"field_64d154fe2b672","section_3_list_4_Name":"أفراد العائلة المعتمدين","_section_3_list_4_Name":"field_64d154fe2bbaf","section_3_list_4_Description":"الأزواج والأطفال دون سن 21 عامًا","_section_3_list_4_Description":"field_64d154fe2bdcb","section_4_card_0_Image":{"post_title":"Business man signing a paper with pen representing simple process and wealth protection","post_content":"","post_excerpt":"","url":"https:\/\/www.citizenshipinvest.com\/wp-content\/uploads\/2023\/08\/card-1-x62-GN5pO-transformed-128.webp","_wp_attachment_image_alt":"Business man signing a paper with pen representing simple process and wealth protection."},"_section_4_card_0_Image":"field_64d15500e4dc4","section_4_card_0_Title":"عملية بسيطة","_section_4_card_0_Title":"field_64d15500e4e38","section_4_card_0_title_2":"","_section_4_card_0_title_2":"field_64d15500e4e8a","section_4_card_0_description":"لا يلزمك الإقامة في اليونان جسديًا.<br><br> لا يتطلب المقابلة أو اختبار الكفاءة في اللغة.<br><br> لا يوجد متطلبات للتعليم أو الخبرة في الإدارة.","_section_4_card_0_description":"field_64d15500e4ed8","section_4_card_0_button":"اقرأ المزيد","_section_4_card_0_button":"field_64d15500e503e","section_4_card_0_link":"","_section_4_card_0_link":"field_649474bb21fa8","section_4_card_1_Image":{"post_title":"A plane and a globe showing global mobility for Malta Residency by Investment","post_content":"","post_excerpt":"","url":"https:\/\/www.citizenshipinvest.com\/wp-content\/uploads\/2023\/09\/v2-1.webp","_wp_attachment_image_alt":"A plane and a globe showing global mobility for Malta Residency by Investment"},"_section_4_card_1_Image":"field_64d15500e4dc4","section_4_card_1_Title":"الحركة العالمية","_section_4_card_1_Title":"field_64d15500e4e38","section_4_card_1_title_2":"","_section_4_card_1_title_2":"field_64d15500e4e8a","section_4_card_1_description":"تقدم التأشيرة الذهبية اليونانية السفر داخل منطقة شنغن بدون مستندات أو تأشيرات إضافية. <br><br> البرنامج يسمح أيضًا لك بالإقامة في أي بلد شنغن آخر لمدة ثلاثة أشهر كل ستة أشهر، بحق الدخول المتعدد.","_section_4_card_1_description":"field_64d15500e4ed8","section_4_card_1_button":"اقرأ المزيد","_section_4_card_1_button":"field_64d15500e503e","section_4_card_1_link":"","_section_4_card_1_link":"field_649474bb21fa8","section_4_card_2_Image":{"post_title":"Wealth-protection-in-greece (1)","post_content":"","post_excerpt":"","url":"https:\/\/www.citizenshipinvest.com\/wp-content\/uploads\/2023\/09\/Wealth-protection-in-greece-1.webp","_wp_attachment_image_alt":"Wealth-protection"},"_section_4_card_2_Image":"field_64d15500e4dc4","section_4_card_2_Title":"حماية الثروة","_section_4_card_2_Title":"field_64d15500e4e38","section_4_card_2_title_2":"","_section_4_card_2_title_2":"field_64d15500e4e8a","section_4_card_2_description":"لا يخضع غير المقيمين لضرائب الدخل في اليونان، باستثناء الإيرادات المتولدة عن تأجير الممتلكات في اليونان.","_section_4_card_2_description":"field_64d15500e4ed8","section_4_card_2_button":"اقرأ المزيد","_section_4_card_2_button":"field_64d15500e503e","section_4_card_2_link":"","_section_4_card_2_link":"field_649474bb21fa8","section_7_options_0_title":"OPTION 1","_section_7_options_0_title":"field_64d1550674a39","section_7_options_0_title_2":"الاستثمار العقاري في اليونان","_section_7_options_0_title_2":"field_64d1550674a98","section_7_options_0_description":"قبل التقدم بطلب للحصول على إقامة في اليونان، يحتاج المستثمرون لشراء الممتلكات العقارية.","_section_7_options_0_description":"field_64d1550674af8","section_7_options_0_list":"1","_section_7_options_0_list":"field_64d1550674b58","section_7_options_0_title_3":"الرسوم الحكومية","_section_7_options_0_title_3":"field_64d1550674bb4","section_7_options_0_description_2":" هناك رسوم حكومية يجب دفعها بالإضافة إلى الحصول على الممتلكات العقارية.","_section_7_options_0_description_2":"field_64d1550674c06","section_7_options_0_list_2":"1","_section_7_options_0_list_2":"field_64d1550674c4e","section_8_list_0_name":"رسوم العناية الواجبة لكل طلب","_section_8_list_0_name":"field_64d1550b2dbf9","section_8_list_0_amount":"5000 دولار أمريكي","_section_8_list_0_amount":"field_64d1550b2dc63","section_8_list_2_0_list_content":"التحقق من الهوية","_section_8_list_2_0_list_content":"field_64d1550d6626e","section_8_list_2_1_list_content":"فحوصات جنائية في الدول التي قضى فيها المتقدم أكثر من 6 أشهر في السنوات العشر الماضية","_section_8_list_2_1_list_content":"field_64d1550d6626e","section_8_list_2_2_list_content":"الفحوصات على التاريخ المالي، بما في ذلك مصدر النقد للإستثمار","_section_8_list_2_2_list_content":"field_64d1550d6626e","section_8_list_2_3_list_content":"التحقق من السمعة مع السلطات وقواعد البيانات الدولية ذات الصلة.","_section_8_list_2_3_list_content":"field_64d1550d6626e","section_9_list_0_month":"1-2","_section_9_list_0_month":"field_64d1550fc6df6","section_9_list_0_title":"عقد الاحتفاظ واختيار الممتلكات","_section_9_list_0_title":"field_64d1550fc6eb1","section_9_list_0_description":"<strong>أول أسبوعين من الحصول على الإقامة مع سيتيزنشيب انفيست يتضمن الآتي:<\/strong>\r\n\r\nتوقيع عقد الاحتفاظ مع سيتيزنشيب انفيست ودفع الدفعة الأولى من رسوم المحترفين لسيتيزنشيب انفيست\r\n\r\nاختيار الممتلكات في اليونان عن بعد، وسيبدأ سيتيزنشيب انفيست في إعداد الوثائق اللازمة لشراء الممتلكات المطلوبة للتطبيق على الإقامة.","_section_9_list_0_description":"field_64d1550fc6f01","section_9_list_1_month":"2-4","_section_9_list_1_month":"field_64d1550fc6df6","section_9_list_1_title":"ترتيبات السفر والحصول على التأشيرة","_section_9_list_1_title":"field_64d1550fc6eb1","section_9_list_1_description":"للحصول على إقامة في اليونان، يجب على العميل السفر إلى البلد وتختم جواز سفره.\r\n\r\nومع ذلك، إذا لم يكن لدى العميل تأشيرة شنغن، فيجب عليه الحصول على تأشيرة سياحية لليونان من القنصلية اليونانية في بلده الأصل أو إقامته.","_section_9_list_1_description":"field_64d1550fc6f01","section_11_cards_0_title":"غير مواطن من الاتحاد الأوروبي","_section_11_cards_0_title":"field_64d15515cbf01","section_11_cards_0_content":"يجب أن يكون المتقدم غير مواطن للاتحاد الأوروبي.","_section_11_cards_0_content":"field_64d15515cbf71","section_11_cards_1_title":"استثمار في العقارات","_section_11_cards_1_title":"field_64d15515cbf01","section_11_cards_1_content":"قم بعمل استثمار في العقارات بقيمة لا تقل عن 250,000 يورو.","_section_11_cards_1_content":"field_64d15515cbf71","section_11_cards_2_title":"سمات حسنة","_section_11_cards_2_title":"field_64d15515cbf01","section_11_cards_2_content":"يجب على المتقدمين وأفراد العائلة أن يكونوا لديهم سجل جنائي خالٍ وموارد مالية كافية.","_section_11_cards_2_content":"field_64d15515cbf71","section_11_cards_3_title":"الزيارة","_section_11_cards_3_title":"field_64d15515cbf01","section_11_cards_3_content":"يجب على المتقدم أن يكون قد زار اليونان مرة واحدة على الأقل قبل التقدم بطلب للحصول على التأشيرة الذهبية.","_section_11_cards_3_content":"field_64d15515cbf71","section_12_list_0_question":"ما هو المبلغ الذي يتطلب للتأهل لبرنامج التأشيرة الذهبية في اليونان؟","_section_12_list_0_question":"field_64d1551a232e7","section_12_list_0_answer":"ليكن برنامج التأشيرة الذهبية في اليونان، يجب أن يتم توفير استثمار مؤهل. يمكن تحقيق ذلك عن طريق شراء عقار بأقل سعر ممكن قدره 250,000 يورو أو توجيه مبلغ لا يقل عن 400,000 يورو نحو السندات الحكومية أو أسهم الشركات. ومع ذلك، ابتداءً من مايو 2023، زاد الحد الأدنى للاستثمار في العقارات المطلوب للحصول على التأشيرة الذهبية إلى 500,000 يورو (532,000 دولار). تستمر التأشيرة الذهبية لمدة خمس سنوات ويمكن تجديدها بشكل دائم، بشرط الحفاظ على الاستثمار.","_section_12_list_0_answer":"field_64d1551a2334a","section_12_list_1_question":"ما هي المتطلبات للحصول على التأشيرة الذهبية في اليونان بخلاف التأشيرة نفسها؟","_section_12_list_1_question":"field_64d1551a232e7","section_12_list_1_answer":"بجانب الاستثمار، يجب أن تستوفي شروط التأهيل المطلوبة للحصول على التأشيرة الذهبية في اليونان. تشمل هذه المعايير أن يكون المتقدم أكبر من 18 عامًا، وألا يكون لديه سجل جنائي، وأن يكون لديه الموارد المالية للاستثمار. يجب أيضًا أن يكون مواطنًا غير من دول الاتحاد الأوروبي\/المساهمة الاقتصادية الأوروبية، وأن يمتلك تأمينًا صحيًا لنفسه ولأسرته، وأن يقدم المستندات اللازمة للحصول على إقامة في اليونان عن طريق الاستثمار.","_section_12_list_1_answer":"field_64d1551a2334a","section_12_list_2_question":"ما هو مدة صلاحية تأشيرة الإقامة الذهبية في اليونان، وهل يمكن تجديدها؟","_section_12_list_2_question":"field_64d1551a232e7","section_12_list_2_answer":"تأشيرة الإقامة الذهبية في اليونان صالحة لمدة خمس سنوات ويمكن تجديدها بلا حدود طالما تم الحفاظ على الاستثمار. يمكن تجديد تأشيرة الإقامة الذهبية كل خمس سنوات إذا تم الحفاظ على الاستثمار في العقارات اليونانية. على عكس معظم الدول الأخرى التي تقدم تأشيرات ذهبية، ليس عليك العيش في اليونان لتجديد تأشيرة الإقامة الخاصة بك. بسبب عدم وجود تاريخ انتهاء لتأشيرة الإقامة الذهبية، يعرف أيضًا باسم تصريح إقامة. يمكنك التقدم للحصول على الجنسية اليونانية إذا قررت البقاء في اليونان بعد سبع سنوات من الإقامة المستمرة.","_section_12_list_2_answer":"field_64d1551a2334a","section_12_list_3_question":"هل أحتاج إلى معرفة اللغة اليونانية للحصول على التأشيرة الذهبية في اليونان؟","_section_12_list_3_question":"field_64d1551a232e7","section_12_list_3_answer":"لا تحتاج إلى معرفة اللغة اليونانية للحصول على التأشيرة الذهبية في اليونان. إذا كنت تعتزم التقدم للحصول على الجنسية اليونانية بعد سبع سنوات في اليونان، يجب أن تجتاز اختبارات اللغة اليونانية والمواطنة.","_section_12_list_3_answer":"field_64d1551a2334a","section_12_list_4_question":"هل يمكنني العمل في اليونان بتأشيرة الإقامة الذهبية؟","_section_12_list_4_question":"field_64d1551a232e7","section_12_list_4_answer":"الحصول على تأشيرة الإقامة الذهبية في اليونان أو أي بلد آخر في الاتحاد الأوروبي لا يمنح الحق في العمل أو العمل. للأسف، لا تمنح تأشيرة المستثمر اليونانية الحامل الحق في البحث عن عمل في اليونان. ومع ذلك، هناك وسائل بديلة لتحقيق الدخل، مثل تأجير العقار المشترى أو الحصول على فوائد على الاستثمار المقدم.","_section_12_list_4_answer":"field_64d1551a2334a","section_14_list_0_review":"أنا ممتن لاختيار Citizenship Invest لبرنامج التأشيرة الذهبية اليونانية. كان العملية سلسة، والمساعدة المهنية التي تلقيتها جعلتها أسهل. الآن، يمكنني العمل عن بعد مع الاستمتاع بفوائد الإقامة في اليونان.","_section_14_list_0_review":"field_64d1551fbbfff","section_14_list_0_name":"","_section_14_list_0_name":"field_64d1551fbc080","section_14_list_1_review":"مع Citizenship Invest، تحقق حلمي في الحصول على التأشيرة الذهبية اليونانية.\" يتمتع أسرتي الآن بالأمان والوصول إلى الاتحاد الأوروبي بفضل البرنامج. نستمتع حاليًا بمستوى حياة أعلى في اليونان مع استمرار توسيع مصالحنا التجارية العالمية.","_section_14_list_1_review":"field_64d1551fbbfff","section_14_list_1_name":"","_section_14_list_1_name":"field_64d1551fbc080","section_14_list_2_review":"I recommend anyone considering the Greece Golden Visa program to apply through Citizenship Invest. Throughout the process, the CI team was extremely helpful and attentive to every detail. Even during the tough times of COVID-19 restrictions, they were able to get our Golden Visas.","_section_14_list_2_review":"field_64d1551fbbfff","section_14_list_2_name":"","_section_14_list_2_name":"field_64d1551fbc080","section_9_list_0_month_text":"WEEK","_section_9_list_0_month_text":"field_64d1550fc6e5e","section_9_list_1_month_text":"WEEK","_section_9_list_1_month_text":"field_64d1550fc6e5e","section_11_bottom_list_0_title":"Passport and Visa Requirements","_section_11_bottom_list_0_title":"field_64d1551753194","section_11_bottom_list_0_content":"<ul>\r\n \t<li>Certified copy of valid passport<\/li>\r\n \t<li>Schengen Visa<\/li>\r\n<\/ul>","_section_11_bottom_list_0_content":"field_64d1551753271","section_11_bottom_list_1_title":"Health Insurance Requirements","_section_11_bottom_list_1_title":"field_64d1551753194","section_11_bottom_list_1_content":"<ul>\r\n \t<li>International health insurance policy that provides full hospitalisation coverage in a Greek public hospital and covers medical care expenses for the entire duration of your stay.<\/li>\r\n \t<li>Valid Medical Travel Insurance for at least the duration of the Greek Tourist Visa (1 year) and covers medical costs and repatriation in all Schengen countries.<\/li>\r\n<\/ul>","_section_11_bottom_list_1_content":"field_64d1551753271","section_4_card_0_read_more":"","_section_4_card_0_read_more":"field_64d15500e5094","section_4_card_1_read_more":"Obtaining Greek citizenship is possible by physically residing in Greece for seven years, which qualifies you to apply for citizenship.","_section_4_card_1_read_more":"field_64d15500e5094","section_4_card_2_read_more":"اقرأ المزيد","_section_4_card_2_read_more":"field_64d15500e5094","section_5_all_countries_0_continent":"أوروبا","_section_5_all_countries_0_continent":"field_64d1550356136","section_5_all_countries_0_countries":"النمسا<br>بلجيكا<br>كرواتيا<br>جمهورية التشيك<br>الدنمارك<br>استونيا<br>فنلندا<br>فرنسا<br>ألمانيا<br>اليونان<br>هنغاريا<br>آيسلندا<br>إيطاليا<br>لاتفيا<br>ليختنشتاين<br>ليتوانيا<br>لوكسمبورج<br>مالطا<br>هولندا<br>النرويج<br>بولندا<br>البرتغال<br>سلوفاكيا<br>سلوفينيا<br>إسبانيا<br>السويد<br>سويسرا<br>","_section_5_all_countries_0_countries":"field_64d155035619e","section_4_card_0_read_more_status":"0","_section_4_card_0_read_more_status":"field_64d15500e4f69","section_4_card_1_read_more_status":"1","_section_4_card_1_read_more_status":"field_64d15500e4f69","section_4_card_2_read_more_status":"0","_section_4_card_2_read_more_status":"field_64d15500e4f69","section_6_image_thumbnail":{"post_title":"Greece Golden Visa and Living Benefits","post_content":"","post_excerpt":"","url":"https:\/\/www.citizenshipinvest.com\/wp-content\/uploads\/2023\/09\/Greece-Golden-Visa-and-Living-Benefits-1.webp","_wp_attachment_image_alt":"Greece Golden Visa and Living Benefits"},"_section_6_image_thumbnail":"field_64d154f8505dc","section_7_options_0_list_0_name":"الاستثمار الأدنى للحصول على الإقامة الذهبية اليونانية","_section_7_options_0_list_0_name":"field_64d155074305d","section_7_options_0_list_0_amount":"250,000 يورو <br> بالإضافة إلى 16 - 23% من ضريبة القيمة المضافة في اليونان.","_section_7_options_0_list_0_amount":"field_64d15507430cf","_yoast_wpseo_focuskw":"Greek Golden Visa","_yoast_wpseo_title":"Greek Golden Visa %%sep%% Greece Residency by Investment %%sep%% Citizenship Invest","_yoast_wpseo_metadesc":"Get a renewable Greece Residency in 2 months with the Greek Golden Visa through real estate investment with Citizenship Invest. Learn More!","_yoast_wpseo_linkdex":"43","section_7_options_0_list_2_0_name":"الرسوم لكل متقدم","_section_7_options_0_list_2_0_name":"field_64d15508a75f7","section_7_options_0_list_2_0_amount":"500 يورو ","_section_7_options_0_list_2_0_amount":"field_64d15508a765f","section_9_list_2_month":"4-5","_section_9_list_2_month":"field_64d1550fc6df6","section_9_list_2_month_text":"أسبوع","_section_9_list_2_month_text":"field_64d1550fc6e5e","section_9_list_2_title":"شراء العقار وتقديم وثائق الإقامة","_section_9_list_2_title":"field_64d1550fc6eb1","section_9_list_2_description":"بعد أن يقوم المحامون بإعداد أوراق شراء الممتلكات المطلوبة، يجب على المتقدمين تحويل الأموال والضرائب المطلوبة للشراء وإنهاء وتقديم وثائق الإقامة للحكومة. يجب على المتقدمين دفع رسوم الحكومة في هذه المرحلة.\r\n\r\nيتم دفع رسوم تطبيق معالجة الحكومة في هذه المرحلة.\r\n\r\nبالإضافة إلى ذلك، يدفع العميل رسوم المحترف لملف التقديم. عن طريق الاعتماد علينا في طلب الإقامة في اليونان، سنقوم بمعالجة كل هذه الإجراءات بسلاسة واحترافية.","_section_9_list_2_description":"field_64d1550fc6f01","section_12_list_5_question":"ما هي المخاطر المرتبطة بالاستثمار في اليونان من خلال برنامج التأشيرة الذهبية؟","_section_12_list_5_question":"field_64d1551a232e7","section_12_list_5_answer":"مثل جميع برامج الاستثمار، برنامج التأشيرة الذهبية في اليونان يحمل بعض المخاطر. من بين هذه المخاطر هي التغييرات المحتملة في متطلبات الاستثمار، مثل زيادة الاستثمار الأدنى من 250،000 يورو إلى 500،000 يورو، التي بدأ تطبيقها في 1 أغسطس 2023. بالإضافة إلى ذلك، يجب على المستثمرين أيضًا أن يأخذوا في الاعتبار احتمال مواجهة صعوبات مع البنوك اليونانية.","_section_12_list_5_answer":"field_64d1551a2334a","_dp_original":"14581","_edit_lock":"1694690409:13","_edit_last":"13","section_11_bottom_list_2_title":"متطلبات وثائق إضافية","_section_11_bottom_list_2_title":"field_64d1551753194","section_11_bottom_list_2_content":"<ul>\r\n \t<li>سجل الولادة الأصلي أو نسخة معتمدة من شهادة الولادة بترجمة رسمية باللغة اليونانية أو الإنجليزية، مصدقة أو مستوفاة من القنصلية اليونانية. يجب على المتقدمين الذين لا يظهر اسم والدهم في وثائق الولادة تقديم كتاب عناوين العائلة.<\/li>\r\n \t<li>حجز تذكرة طيران لزيارة اليونان (غير مطلوبة بالضرورة)<\/li>\r\n \t<li>دليل على إقامة في فندق أو رسالة دعوة من قريب أو صديق لإثبات الوجهة وغرض الرحلة.<\/li>\r\n \t<li>ثلاث صور شخصية بحجم جواز السفر الأصلية<\/li>\r\n<\/ul>","_section_11_bottom_list_2_content":"field_64d1551753271","section_11_bottom_list_3_title":"الوثائق المطلوبة فقط من المتقدم الرئيسي","_section_11_bottom_list_3_title":"field_64d1551753194","section_11_bottom_list_3_content":"<strong>دليل على العنوان:<\/strong>\r\n\r\n<ul>\r\n \t<li>تقديم فاتورة المرافق الرسمية التي تظهر العنوان السكني. ويجب على المتقدم الحصول على ترجمة رسمية باللغة الإنجليزية أو اليونانية وتصديقها من القنصلية اليونانية لمكان الإقامة.<\/li>\r\n<\/ul>\r\n<strong>دليل على العمل والدخل:<\/strong>\r\n\r\n<ul>\r\n \t<li>مطلوب دليل على العمل أو دليل على الشركة الشخصية والدخل.<\/li>\r\n \t<li>يجب أن يثبت المستند الرسمي أيضًا عنوان عمل المتقدم ونوع العمل والدخل السنوي. ويجب على المتقدم الحصول على ترجمة رسمية باللغة الإنجليزية أو اليونانية وتصديقها من القنصلية اليونانية لمكان الإقامة.<\/li>\r\n<\/ul>\r\n<strong>كشف حساب بنكي:<\/strong>\r\n\r\n<ul>\r\n \t<li>مطلوب كشف حساب بنكي لآخر ستة أشهر.<\/li>\r\n<\/ul>","_section_11_bottom_list_3_content":"field_64d1551753271","section_11_bottom_list_4_title":"إذا قدم الأزواج المتزوجون طلبًا مشتركًا للحصول على تأشيرة الذهب اليونانية، فيجب أن يقدموا الوثائق التالية","_section_11_bottom_list_4_title":"field_64d1551753194","section_11_bottom_list_4_content":"<strong>وثائق الزواج<\/strong>\r\n\r\n<ul>\r\n \t<li>يجب على الأزواج تقديم مقتطف أصلي من سجل الزواج أو نسخة معتمدة من شهادات الزواج مع ترجمة رسمية باللغة اليونانية أو الإنجليزية.<\/li>\r\n \t<li>يجب أن تكون هذه الوثائق مصدقة أو مستوفاة بواسطة القنصلية اليونانية.<\/li>\r\n<\/ul>\r\n<strong>مستندات الطلاق<\/strong>\r\n\r\n<ul>\r\n \t<li>يجب على المتقدمين تقديم نسخة معتمدة من وثيقة الطلاق.<\/li>\r\n \t<li>يجب أن يتم تصديق أو مثبتة بواسطة القنصلية اليونانية إذا كانوا مطلقين سابقًا.<\/li>\r\n<\/ul>","_section_11_bottom_list_4_content":"field_64d1551753271","section_9_list_3_month":"٣-٤","_section_9_list_3_month":"field_64d1550fc6df6","section_9_list_3_month_text":"MONTH ","_section_9_list_3_month_text":"field_64d1550fc6e5e","section_9_list_3_title":"Residency Permit Approval and Issuance","_section_9_list_3_title":"field_64d1550fc6eb1","section_9_list_3_description":"Residency Permit approval takes two months.\r\n\r\nTo obtain Greek residency, the client must pay the CI Professional Fees before issuance of the residence permit.\r\n\r\nApproved clients can send passports for permit insertion or travel to Greece.\r\n\r\nAfter approval, clients can send passports to CI lawyers in Greece or travel there to insert the residency permit. Working with experienced professionals is crucial for successful application and enjoying the benefits of living in Greece.\r\n\r\nResidence visa approval time varies based on due diligence and case specifics.","_section_9_list_3_description":"field_64d1550fc6f01","section_12_list_6_question":"What happens if my investment in Greece fails or loses value?","_section_12_list_6_question":"field_64d1551a232e7","section_12_list_6_answer":"If your investment in Greece fails or loses value, you may face financial losses and potential difficulties in recovering your investment. The Greek Golden Visa program requires a qualifying investment in real estate or government bonds; if the investment fails or loses value, you may lose your residency permit.","_section_12_list_6_answer":"field_64d1551a2334a","section_12_list_7_question":"Are there any tax implications for investors under the Golden Visa program in Greece?","_section_12_list_7_question":"field_64d1551a232e7","section_12_list_7_answer":"Under the Greek Golden Visa program, investors can keep their non-Greek tax residency and pay taxes only on income earned in Greece, not money earned elsewhere. Greece also has a \"non-domicile\" program for those who have residence elsewhere but are still Greek residents, imposing a flat tax of €100,000 on shipowners, businesses, and retired foreign investors over 15 years. Furthermore, according to the Greek double taxation treaty, income earned outside Greece while living in Greece is not taxed. However, rental income from real estate in Greece is taxed at a progressive rate ranging from 15% (for income up to €12,000) to 45%.","_section_12_list_7_answer":"field_64d1551a2334a","section_14_list_3_review":"I was blessed to enjoy the benefits of the Greece Residency by Investment Program.\" It was a good choice for my family because of the financial prospects, tax breaks, and residence benefits. And having Citizenship Invest has made the process quick, secure, and simple.","_section_14_list_3_review":"field_64d1551fbbfff","section_14_list_3_name":"","_section_14_list_3_name":"field_64d1551fbc080","show_or_hide_countries":"1","_show_or_hide_countries":"field_64ee8f3a50657","_wpml_media_has_media":"1","section_7_options_0_read_more_status":"0","_section_7_options_0_read_more_status":"field_6501b51721a58","section_7_options_0_button":"","_section_7_options_0_button":"field_6501b52721a59","section_7_options_0_read_more":"اقرأ المزيد","_section_7_options_0_read_more":"field_6501b52e21a5a","section_2_tab_1_title":"سرعة الاستجابة","section_2_tab_1_description":"نقوم بالرد على استفسارات عملائنا بسرعة كبيرة.","section_2_tab_2_title":"دعم مستمر","section_2_tab_2_description":"نحن هنا لمساعدة عملائنا على مراحل العملية بشكل مستمر.","section_2_tab_3_title":"مهنية","section_2_tab_3_description":"نحن فريق محترف يسعى لتحقيق أفضل النتائج لعملائنا.","section_3_subtitle":"استثمر في المستقبل واحصل على الجنسية","section_3_box_1_title":"برنامج #1","section_3_box_1_description":"احصل على جنسية قوية ومرغوبة.","section_3_box_2_title":"برنامج #2","section_3_box_2_description":"استثمر في العقارات واحصل على الجنسية.","section_3_box_3_title":"برنامج #3","section_3_box_3_description":"تجنب الضرائب واحصل على الحماية الجنائية.","section_4_box_1_title":"تجربة ممتازة","section_4_box_1_description":"حصلت على جنسية ثانية بسرعة وبسهولة.","section_4_box_2_title":"فريق ممتاز","section_4_box_2_description":"فريق محترف ومتفاني يقدم خدمة رائعة.","section_4_box_3_title":"أفضل خدمة عملاء","section_4_box_3_description":"تجربة فريدة ورائعة مع فريق الدعم.","section_6_terms":"شروط الاستخدام","section_6_privacy":"سياسة الخصوصية","section_7_options_1_get_started":"ابدأ الآن","section_8_why_choose_us":"لماذا اختيارنا؟","section_8_why_choose_us_description":"نحن شركة سيتيزنشيب انفيست المتخصصة في توفير برامج الجنسية للمستثمرين الأجانب. نحن نقدم خدمات عالية الجودة تهدف إلى تلبية احتياجات عملائنا وتوفير حلول سريعة وموثوقة. نحن فريق محترف ومتفانٍ نعمل بكفاءة وتفانٍ لضمان تجربة استثمارية استثنائية ونتائج ناجحة. اتصل بنا اليوم للحصول على استشارة مجانية وابدأ رحلتك نحو الحصول على الجنسية الثانية."},"terms":[[{"term_id":16,"name":"Optional","slug":"optional","term_group":0,"term_taxonomy_id":16,"taxonomy":"translation_priority","description":"","parent":0,"count":232,"filter":"raw"}]],"source_domain":"https:\/\/www.citizenshipinvest.com\/en\/"}]